viavi/fibermark/__init__.py
viavi/fibermark/cli.py
viavi/fibermark/cli_commands/add.py
viavi/fibermark/cli_commands/compare.py
viavi/fibermark/cli_commands/filtering_helpers.py
viavi/fibermark/cli_commands/note.py
viavi/fibermark/cli_commands/remote.py
viavi/fibermark/cli_commands/show.py
viavi/fibermark/cli_commands/update.py
viavi/fibermark/db_utils/HelperTypesDB.py
viavi/fibermark/db_utils/__init__.py
viavi/fibermark/db_utils/connect.py
viavi/fibermark/db_utils/converters.py
viavi/fibermark/db_utils/db_insertion.py
viavi/fibermark/db_utils/orm.py
viavi/fibermark/db_utils/ping_db.py
viavi/fibermark/db_utils/query_helpers.py
viavi/fibermark/db_utils/settings.py
viavi/fibermark/db_utils/test_connect.py
viavi/fibermark/notation/algo.py
viavi/fibermark/notation/comparison.py
viavi/fibermark/notation/detailed_reports_comparisons.py
viavi/fibermark/notation/helpers.py
viavi/fibermark/notation/measure.py
viavi/fibermark/notation/stats_helpers.py
viavi/fibermark/notation/threshold.py
viavi/fibermark/scripts/create_db_from_folder_sor_files.py
viavi/fibermark/scripts/dump_new_version_sor_data.py
viavi/fibermark/scripts/fo_notation.py
viavi/fibermark/scripts/inspect_folder_measure_results.py
viavi/fibermark/scripts/restore_prof_v2.py
viavi/fibermark/scripts/update_ref_parsed_sor_data.py
viavi/fibermark/scripts/upload_new_sor_files_to_db.py
viavi/fibermark/utils/calculate_md5.py
viavi/fibermark/utils/fake.sor
viavi/fibermark/utils/fo_eval_helpers.py
viavi/fibermark/utils/ftp_helpers.py
viavi/fibermark/utils/helpers.py
viavi/fibermark/utils/logging.py
viavi/fibermark/utils/parser_selector.py
viavi/fibermark/utils/platform_helpers.py
viavi/fibermark/utils/sor_data_converters.py
viavi_fibermark-0.1.1.dist-info/METADATA
viavi_fibermark-0.1.1.dist-info/WHEEL
viavi_fibermark-0.1.1.dist-info/entry_points.txt
viavi_fibermark-0.1.1.dist-info/RECORD
