Metadata-Version: 2.1
Name: viavi.fibermark
Version: 0.1.1
Summary: 
Author: Aboussejra
Author-email: Amir.Boussejra@viavisolutions.com
Requires-Python: >=3.9,<4.0
Classifier: Programming Language :: Python :: 3
Classifier: Programming Language :: Python :: 3.9
Classifier: Programming Language :: Python :: 3.10
Classifier: Programming Language :: Python :: 3.11
Classifier: Programming Language :: Python :: 3.12
Requires-Dist: click (>=8.1.3,<9.0.0)
Requires-Dist: cloup (>=2.0.0.post1,<3.0.0)
Requires-Dist: coloredlogs (>=15.0.1,<16.0.0)
Requires-Dist: ftputil (>=5.0.4,<6.0.0)
Requires-Dist: jinja2 (>=3.1.2,<4.0.0)
Requires-Dist: numpy (>=1.20)
Requires-Dist: openpyxl (>=3.1.2,<4.0.0)
Requires-Dist: pandas (>=2.0.3,<3.0.0)
Requires-Dist: pydantic (>=1.10.13)
Requires-Dist: pymysql (>=1.0.3,<2.0.0)
Requires-Dist: result (>=0.9.0,<0.10.0)
Requires-Dist: sqlalchemy-utils (>=0.41.1,<0.42.0)
Requires-Dist: sqlalchemy[mypy] (>=2.0.9,<3.0.0)
Requires-Dist: tabulate (>=0.9.0,<0.10.0)
Requires-Dist: termcolor (>=2.2.0,<3.0.0)
Requires-Dist: type-checker-decorators (>=0.1.3,<0.2.0)
Requires-Dist: types-tabulate (>=0.9.0.2,<0.10.0.0)
Requires-Dist: viavi-fiberparse (>=0.1.0,<0.2.0)
Requires-Dist: viavi-placopy (>=1.2.3,<2.0.0)
Requires-Dist: xlsxwriter (>=3.1.2,<4.0.0)
